Workbook

Sheet Income Statement
A1: Titan Company - Income Statement 4 (₹ Cr)
B3: FY22 | C3: FY23 | D3: FY24 | E3: FY25 | F3: FY26 | G3: FY27E | H3: FY28E | I3: FY29E
A4: Revenue | B4: 28799 | C4: 40575 | D4: 51084 | E4: 60456 | F4: 87584 | G4: =F4*1.2 -> 105100.8 | H4: =G4*1.2 -> 126120.96 | I4: =H4*1.2 -> 151345.15
A5: Total Expenses | B5: 25455 | C5: 35693 | D5: 45792 | E5: 54762 | F5: 79229 | G5: =G4*0.9 -> 94590.72 | H5: =H4*0.9 -> 113508.86 | I5: =I4*0.9 -> 136210.64
A6: Operating Profit (EBIDTA) | B6: =B4-B5 -> 3344 | C6: =C4-C5 -> 4882 | D6: =D4-D5 -> 5292 | E6: =E4-E5 -> 5694 | F6: =F4-F5 -> 8355 | G6: =G4-G5 -> 10510.08 | H6: =H4-H5 -> 12612.096 | I6: =I4-I5 -> 15134.515
A7: Other Income | B7: 177 | C7: 306 | D7: 534 | E7: 487 | F7: 452 | G7: 452 | H7: 452 | I7: 452
A8: Depreciation | B8: 399 | C8: 441 | D8: 584 | E8: 693 | F8: 826 | G8: =F8*1.1 -> 908.6 | H8: =G8*1.1 -> 999.46 | I8: =H8*1.1 -> 1099.406
A9: Interest | B9: 218 | C9: 380 | D9: 619 | E9: 953 | F9: 1180 | G9: =F9*1.5 -> 1770 | H9: =G9*1.5 -> 2655 | I9: =H9*1.5 -> 3982.5
A10: Profit Before Tax | B10: =B6+B7-B8-B9 -> 2904 | C10: =C6+C7-C8-C9 -> 4367 | D10: =D6+D7-D8-D9 -> 4623 | E10: =E6+E7-E8-E9 -> 4535 | F10: =F6+F7-F8-F9 -> 6801 | G10: =G6+G7-G8-G9 -> 8283.48 | H10: =H6+H7-H8-H9 -> 9409.636 | I10: =I6+I7-I8-I9 -> 10504.609
A11: Tax% | B11: 0.24 | C11: 0.26 | D11: 0.24 | E11: 0.26 | F11: 0.25 | G11: 0.25 | H11: 0.25 | I11: 0.25
A12: Net Profit | B12: =B10-(B10*B11) -> 2207.04 | C12: =C10-(C10*C11) -> 3231.58 | D12: =D10-(D10*D11) -> 3513.48 | E12: =E10-(E10*E11) -> 3355.9 | F12: =F10-(F10*F11) -> 5100.75 | G12: =G10-(G10*G11) -> 6212.61 | H12: =H10-(H10*H11) -> 7057.227 | I12: =I10-(I10*I11) -> 7878.4569
A15: Revenue Growth% | C15: =(C4-B4)/B4 -> 0.40890309 | D15: =(D4-C4)/C4 -> 0.25900185 | E15: =(E4-D4)/D4 -> 0.18346253 | F15: =(F4-E4)/E4 -> 0.44872304 | G15: 0.2 | H15: 0.2 | I15: 0.2
A16: Expense % of Revenue. | B16: =B5/B4 -> 0.88388486 | C16: =C5/C4 -> 0.87967961 | D16: =D5/D4 -> 0.89640592 | E16: =E5/E4 -> 0.9058158 | F16: =F5/F4 -> 0.90460586 | G16: =G5/G4 -> 0.9 | H16: =H5/H4 -> 0.9 | I16: =I5/I4 -> 0.9

Sheet Balance Sheet
A1: Titan Company - Balance Sheet(₹ Cr)
B3: FY22 | C3: FY23 | D3: FY24 | E3: FY25 | F3: FY26 | G3: FY27E | H3: FY28E | I3: FY29E
A4: Equity Share Capital | B4: 89 | C4: 89 | D4: 89 | E4: 89 | F4: 89 | G4: =F4 -> 89 | H4: =G4 -> 89 | I4: =H4 -> 89
A5: Reserves | B5: 9214 | C5: 11762 | D5: 9304 | E5: 11535 | F5: 15614 | G5: =F5+'Income Statement'!G12 -> 21826.61 | H5: =G5+'Income Statement'!H12 -> 28883.837 | I5: =H5+'Income Statement'!I12 -> 36762.294
A6: Borrowings | B6: 7275 | C6: 9367 | D6: 15528 | E6: 20777 | F6: 14551 | G6: =F6*1.05 -> 15278.55 | H6: =G6*1.05 -> 16042.478 | I6: =H6*1.05 -> 16844.601
A7: Other Liabilities | B7: 4610 | C7: 5802 | D7: 6626 | E7: 8244 | F7: 30307 | G7: =F7*1.05 -> 31822.35 | H7: =G7*1.05 -> 33413.467 | I7: =H7*1.05 -> 35084.141
A8: Total Liabilities | B8: =SUM(B4:B7) -> 21188 | C8: =SUM(C4:C7) -> 27020 | D8: =SUM(D4:D7) -> 31547 | E8: =SUM(E4:E7) -> 40645 | F8: =SUM(F4:F7) -> 60561 | G8: =SUM(G4:G7) -> 69016.51 | H8: =SUM(H4:H7) -> 78428.782 | I8: =SUM(I4:I7) -> 88780.036
A10: Fixed Assets | B10: 2544 | C10: 2998 | D10: 3709 | E10: 4062 | F10: 6906 | G10: =F10*1.1 -> 7596.6 | H10: =G10*1.1 -> 8356.26 | I10: =H10*1.1 -> 9191.886
A11: CWIP | B11: 85 | C11: 144 | D11: 97 | E11: 105 | F11: 135 | G11: =F11*1.1 -> 148.5 | H11: =G11*1.1 -> 163.35 | I11: =H11*1.1 -> 179.685
A12: Investments | B12: 294 | C12: 2515 | D12: 2345 | E12: 1988 | F12: 3506 | G12: =F12*1.1 -> 3856.6 | H12: =G12*1.1 -> 4242.26 | I12: =H12*1.1 -> 4666.486
A13: Other Assets | B13: 18265 | C13: 21363 | D13: 25396 | E13: 34490 | F13: 50014 | G13: =F13*1.15 -> 57516.1 | H13: =G13*1.15 -> 66143.515 | I13: =H13*1.15 -> 76065.042
A14: Total Assets | B14: =SUM(B10:B13) -> 21188 | C14: =SUM(C10:C13) -> 27020 | D14: =SUM(D10:D13) -> 31547 | E14: =SUM(E10:E13) -> 40645 | F14: =SUM(F10:F13) -> 60561 | G14: =SUM(G10:G13) -> 69117.8 | H14: =SUM(H10:H13) -> 78905.385 | I14: =SUM(I10:I13) -> 90103.099

Sheet Cash Flow
A1: Titan Company - Cash Flow Statement(₹ Cr)
B3: FY22 | C3: FY23 | D3: FY24 | E3: FY25 | F3: FY26 | G3: FY27E | H3: FY28E | I3: FY29E
A4: Cash From Operating Activities | B4: -724 | C4: 1370 | D4: 1695 | E4: -541 | F4: 5590 | G4: =F4*1.2 -> 6708 | H4: =G4*1.2 -> 8049.6 | I4: =H4*1.2 -> 9659.52
A5: Cash From Investing Activities | B5: 1165 | C5: -1814 | D5: -189 | E5: 546 | F5: -2934 | G5: =-G10 -> -690.6 | H5: =-H10 -> -759.66 | I5: =-I10 -> -835.626
A6: Cash From Financing Activities | B6: -403 | C6: 457 | D6: -1329 | E6: -7 | F6: -2159 | G6: -2159 | H6: -2159 | I6: -2159
A7: Net Cash Flow | B7: 38 | C7: 13 | D7: 177 | E7: -2 | F7: 497 | G7: =SUM(G4:G6) -> 3858.4 | H7: =SUM(H4:H6) -> 5130.94 | I7: =SUM(I4:I6) -> 6664.894
A8: Free Cash Flow | B8: -940 | C8: 950 | D8: 1024 | E8: -1011 | F8: 4713 | G8: =G4-G10 -> 6017.4 | H8: =H4-H10 -> 7289.94 | I8: =I4-I10 -> 8823.894
A9: CFO/OP | B9: 0.02 | C9: 0.52 | D9: 0.54 | E9: 0.1 | F9: 0.88 | G9: =G4/'Income Statement'!G6 -> 0.63824443 | H9: =H4/'Income Statement'!H6 -> 0.63824443 | I9: =I4/'Income Statement'!I6 -> 0.63824443
A10: Capex(Approx) | C10: ='Balance Sheet'!C10-'Balance Sheet'!B10 -> 454 | D10: ='Balance Sheet'!D10-'Balance Sheet'!C10 -> 711 | E10: ='Balance Sheet'!E10-'Balance Sheet'!D10 -> 353 | F10: ='Balance Sheet'!F10-'Balance Sheet'!E10 -> 2844 | G10: ='Balance Sheet'!G10-'Balance Sheet'!F10 -> 690.6 | H10: ='Balance Sheet'!H10-'Balance Sheet'!G10 -> 759.66 | I10: ='Balance Sheet'!I10-'Balance Sheet'!H10 -> 835.626
